odoo9_addon_mis_builder_budget-9.0.3.4.0-nspkg.pth
odoo_addons/mis_builder_budget/README.rst
odoo_addons/mis_builder_budget/__init__.py
odoo_addons/mis_builder_budget/__openerp__.py
odoo_addons/mis_builder_budget/i18n/ca.po
odoo_addons/mis_builder_budget/i18n/de.po
odoo_addons/mis_builder_budget/i18n/es.po
odoo_addons/mis_builder_budget/i18n/fr.po
odoo_addons/mis_builder_budget/i18n/mis_builder_budget.pot
odoo_addons/mis_builder_budget/i18n/nl.po
odoo_addons/mis_builder_budget/i18n/nl_NL.po
odoo_addons/mis_builder_budget/i18n/pt.po
odoo_addons/mis_builder_budget/models/__init__.py
odoo_addons/mis_builder_budget/models/mis_budget.py
odoo_addons/mis_builder_budget/models/mis_budget_item.py
odoo_addons/mis_builder_budget/models/mis_report_instance.py
odoo_addons/mis_builder_budget/models/mis_report_instance_period.py
odoo_addons/mis_builder_budget/models/mis_report_kpi.py
odoo_addons/mis_builder_budget/models/mis_report_kpi_expression.py
odoo_addons/mis_builder_budget/readme/CONTRIBUTORS.rst
odoo_addons/mis_builder_budget/readme/DESCRIPTION.rst
odoo_addons/mis_builder_budget/readme/HISTORY.rst
odoo_addons/mis_builder_budget/readme/ROADMAP.rst
odoo_addons/mis_builder_budget/readme/USAGE.rst
odoo_addons/mis_builder_budget/readme/newsfragments/.gitignore
odoo_addons/mis_builder_budget/security/mis_budget.xml
odoo_addons/mis_builder_budget/security/mis_budget_item.xml
odoo_addons/mis_builder_budget/static/description/icon.png
odoo_addons/mis_builder_budget/static/description/index.html
odoo_addons/mis_builder_budget/tests/__init__.py
odoo_addons/mis_builder_budget/tests/test_mis_budget.py
odoo_addons/mis_builder_budget/views/mis_budget.xml
odoo_addons/mis_builder_budget/views/mis_budget_item.xml
odoo_addons/mis_builder_budget/views/mis_report.xml
odoo_addons/mis_builder_budget/views/mis_report_instance_period.xml
odoo9_addon_mis_builder_budget-9.0.3.4.0.dist-info/METADATA
odoo9_addon_mis_builder_budget-9.0.3.4.0.dist-info/WHEEL
odoo9_addon_mis_builder_budget-9.0.3.4.0.dist-info/namespace_packages.txt
odoo9_addon_mis_builder_budget-9.0.3.4.0.dist-info/top_level.txt
odoo9_addon_mis_builder_budget-9.0.3.4.0.dist-info/RECORD
