Metadata-Version: 2.1
Name: odoo9-addon-mis-builder-budget
Version: 9.0.3.4.0
Summary: Create budgets for MIS reports
Home-page: https://github.com/OCA/mis-builder/
Author: ACSONE SA/NV, Odoo Community Association (OCA)
Author-email: support@odoo-community.org
License: AGPL-3
Platform: UNKNOWN
Classifier: Programming Language :: Python
Classifier: Framework :: Odoo
Classifier: License :: OSI Approved :: GNU Affero General Public License v3
Classifier: Development Status :: 5 - Production/Stable
Requires-Python: ~=2.7
Requires-Dist: odoo9-addon-mis-builder
Requires-Dist: odoo (<9.1a,>=9.0a)
